oly/__init__.py
oly/bitbucket.py
oly/cli.py
oly/config.py
oly/docker.py
oly/help.py
oly/service.py
oly/setup.py
oly/utils.py
oly/version.txt
oly/tools/mongo/Dockerfile
oly/tools/mongo/mongo.yml
oly/tools/mysql/Dockerfile
oly/tools/mysql/my.cnf
oly/tools/mysql/mysql.yml
oly/tools/postgres/Dockerfile
oly/tools/postgres/postgres.yml
oly/tools/rabbitmq/Dockerfile
oly/tools/rabbitmq/rabbitmq.yml
oly/tools/redis/Dockerfile
oly/tools/redis/redis.yml
oly/tools/swagger/Dockerfile
oly/tools/swagger/swagger.yml
oly-1.0.33.dist-info/LICENSE
oly-1.0.33.dist-info/METADATA
oly-1.0.33.dist-info/WHEEL
oly-1.0.33.dist-info/entry_points.txt
oly-1.0.33.dist-info/top_level.txt
oly-1.0.33.dist-info/RECORD
