Metadata-Version: 2.1
Name: oly
Version: 1.0.33
Summary: Oly Cli
Home-page: https://github.com/glikaj/oly
Author: Genci Likaj
Author-email: genci.likaj@gmail.com
License: MIT
Project-URL: Source, https://github.com/glikaj/oly/
Project-URL: Tracker, https://github.com/glikaj/oly/issues
Keywords: cli development console docker
Platform: UNKNOWN
Classifier: Development Status :: 3 - Alpha
Classifier: Intended Audience :: Developers
Classifier: Programming Language :: Python
Classifier: Programming Language :: Python :: 2
Classifier: Programming Language :: Python :: 2.7
Classifier: Programming Language :: Python :: 3
Classifier: Programming Language :: Python :: 3.4
Classifier: Programming Language :: Python :: 3.5
Classifier: Programming Language :: Python :: 3.6
Classifier: Programming Language :: Python :: 3.7
Classifier: License :: OSI Approved :: MIT License
Classifier: Operating System :: OS Independent
Requires-Dist: click
Requires-Dist: requests
Requires-Dist: tabulate
